[
  {
    "quote": "The best way to find yourself is to lose yourself in the service of others.",
    "author": "Mahatma Gandhi",
    "title": "Independence Leader & Philosopher"
  },
  {
    "quote": "Darkness cannot drive out darkness; only light can do that. Hate cannot drive out hate; only love can do that.",
    "author": "Martin Luther King Jr.",
    "title": "Civil Rights Leader"
  },
  {
    "quote": "The only thing necessary for the triumph of evil is for good men to do nothing.",
    "author": "Edmund Burke",
    "title": "Philosopher & Statesman"
  },
  {
    "quote": "In the middle of difficulty lies opportunity.",
    "author": "Albert Einstein",
    "title": "Theoretical Physicist"
  },
  {
    "quote": "The future belongs to those who believe in the beauty of their dreams.",
    "author": "Eleanor Roosevelt",
    "title": "Diplomat & Human Rights Advocate"
  },
  {
    "quote": "It always seems impossible until it's done.",
    "author": "Nelson Mandela",
    "title": "Anti-Apartheid Revolutionary & President"
  },
  {
    "quote": "Be the change that you wish to see in the world.",
    "author": "Mahatma Gandhi",
    "title": "Independence Leader & Philosopher"
  },
  {
    "quote": "Education is the most powerful weapon which you can use to change the world.",
    "author": "Nelson Mandela",
    "title": "Anti-Apartheid Revolutionary & President"
  },
  {
    "quote": "The only way to do great work is to love what you do.",
    "author": "Steve Jobs",
    "title": "Technology Innovator"
  },
  {
    "quote": "Life is what happens when you're busy making other plans.",
    "author": "John Lennon",
    "title": "Musician & Peace Activist"
  },
  {
    "quote": "The mind is everything. What you think you become.",
    "author": "Buddha",
    "title": "Spiritual Teacher"
  },
  {
    "quote": "You must be the change you wish to see in the world.",
    "author": "Mahatma Gandhi",
    "title": "Independence Leader & Philosopher"
  },
  {
    "quote": "Nothing in life is to be feared, it is only to be understood.",
    "author": "Marie Curie",
    "title": "Physicist & Chemist"
  },
  {
    "quote": "The greatest glory in living lies not in never falling, but in rising every time we fall.",
    "author": "Nelson Mandela",
    "title": "Anti-Apartheid Revolutionary & President"
  },
  {
    "quote": "Do not dwell in the past, do not dream of the future, concentrate the mind on the present moment.",
    "author": "Buddha",
    "title": "Spiritual Teacher"
  },
  {
    "quote": "Everything you've ever wanted is on the other side of fear.",
    "author": "George Addair",
    "title": "Motivational Pioneer"
  },
  {
    "quote": "Believe you can and you're halfway there.",
    "author": "Theodore Roosevelt",
    "title": "26th U.S. President"
  },
  {
    "quote": "The only impossible journey is the one you never begin.",
    "author": "Tony Robbins",
    "title": "Motivational Speaker"
  },
  {
    "quote": "In three words I can sum up everything I've learned about life: it goes on.",
    "author": "Robert Frost",
    "title": "Poet"
  },
  {
    "quote": "To live is the rarest thing in the world. Most people exist, that is all.",
    "author": "Oscar Wilde",
    "title": "Playwright & Poet"
  },
  {
    "quote": "The purpose of our lives is to be happy.",
    "author": "Dalai Lama",
    "title": "Spiritual Leader"
  },
  {
    "quote": "Get busy living or get busy dying.",
    "author": "Stephen King",
    "title": "Author"
  },
  {
    "quote": "You only live once, but if you do it right, once is enough.",
    "author": "Mae West",
    "title": "Actress & Playwright"
  },
  {
    "quote": "Many of life's failures are people who did not realize how close they were to success when they gave up.",
    "author": "Thomas Edison",
    "title": "Inventor"
  },
  {
    "quote": "If you want to lift yourself up, lift up someone else.",
    "author": "Booker T. Washington",
    "title": "Educator & Civil Rights Leader"
  },
  {
    "quote": "The way to get started is to quit talking and begin doing.",
    "author": "Walt Disney",
    "title": "Animator & Entrepreneur"
  },
  {
    "quote": "Don't let yesterday take up too much of today.",
    "author": "Will Rogers",
    "title": "Humorist & Social Commentator"
  },
  {
    "quote": "If life were predictable it would cease to be life, and be without flavor.",
    "author": "Eleanor Roosevelt",
    "title": "Diplomat & Human Rights Advocate"
  },
  {
    "quote": "Success is not final, failure is not fatal: it is the courage to continue that counts.",
    "author": "Winston Churchill",
    "title": "British Prime Minister"
  },
  {
    "quote": "It is during our darkest moments that we must focus to see the light.",
    "author": "Aristotle",
    "title": "Philosopher"
  },
  {
    "quote": "Whoever is happy will make others happy too.",
    "author": "Anne Frank",
    "title": "Diarist & Holocaust Victim"
  },
  {
    "quote": "Do not go where the path may lead, go instead where there is no path and leave a trail.",
    "author": "Ralph Waldo Emerson",
    "title": "Philosopher & Poet"
  },
  {
    "quote": "You will face many defeats in life, but never let yourself be defeated.",
    "author": "Maya Angelou",
    "title": "Poet & Civil Rights Activist"
  },
  {
    "quote": "In the end, it's not the years in your life that count. It's the life in your years.",
    "author": "Abraham Lincoln",
    "title": "16th U.S. President"
  },
  {
    "quote": "Never let the fear of striking out keep you from playing the game.",
    "author": "Babe Ruth",
    "title": "Baseball Legend"
  },
  {
    "quote": "Life is either a daring adventure or nothing at all.",
    "author": "Helen Keller",
    "title": "Author & Disability Rights Advocate"
  },
  {
    "quote": "The only person you are destined to become is the person you decide to be.",
    "author": "Ralph Waldo Emerson",
    "title": "Philosopher & Poet"
  },
  {
    "quote": "Not all those who wander are lost.",
    "author": "J.R.R. Tolkien",
    "title": "Author & Scholar"
  },
  {
    "quote": "Life is 10% what happens to me and 90% of how I react to it.",
    "author": "Charles R. Swindoll",
    "title": "Pastor & Author"
  },
  {
    "quote": "The best time to plant a tree was 20 years ago. The second best time is now.",
    "author": "Chinese Proverb",
    "title": "Ancient Wisdom"
  },
  {
    "quote": "An unexamined life is not worth living.",
    "author": "Socrates",
    "title": "Philosopher"
  },
  {
    "quote": "Your time is limited, don't waste it living someone else's life.",
    "author": "Steve Jobs",
    "title": "Technology Innovator"
  },
  {
    "quote": "The greatest wealth is to live content with little.",
    "author": "Plato",
    "title": "Philosopher"
  },
  {
    "quote": "Waste no more time arguing about what a good man should be. Be one.",
    "author": "Marcus Aurelius",
    "title": "Roman Emperor & Philosopher"
  },
  {
    "quote": "You have power over your mind - not outside events. Realize this, and you will find strength.",
    "author": "Marcus Aurelius",
    "title": "Roman Emperor & Philosopher"
  },
  {
    "quote": "The happiness of your life depends upon the quality of your thoughts.",
    "author": "Marcus Aurelius",
    "title": "Roman Emperor & Philosopher"
  },
  {
    "quote": "He who has a why to live can bear almost any how.",
    "author": "Friedrich Nietzsche",
    "title": "Philosopher"
  },
  {
    "quote": "We are what we repeatedly do. Excellence, then, is not an act, but a habit.",
    "author": "Aristotle",
    "title": "Philosopher"
  },
  {
    "quote": "The only true wisdom is in knowing you know nothing.",
    "author": "Socrates",
    "title": "Philosopher"
  },
  {
    "quote": "What worries you, masters you.",
    "author": "John Locke",
    "title": "Philosopher"
  },
  {
    "quote": "I think, therefore I am.",
    "author": "René Descartes",
    "title": "Philosopher & Mathematician"
  },
  {
    "quote": "The unexamined life is not worth living.",
    "author": "Socrates",
    "title": "Philosopher"
  },
  {
    "quote": "Turn your wounds into wisdom.",
    "author": "Oprah Winfrey",
    "title": "Media Executive & Philanthropist"
  },
  {
    "quote": "The journey of a thousand miles begins with one step.",
    "author": "Lao Tzu",
    "title": "Philosopher"
  },
  {
    "quote": "That which does not kill us makes us stronger.",
    "author": "Friedrich Nietzsche",
    "title": "Philosopher"
  },
  {
    "quote": "Be kind, for everyone you meet is fighting a hard battle.",
    "author": "Plato",
    "title": "Philosopher"
  },
  {
    "quote": "I have not failed. I've just found 10,000 ways that won't work.",
    "author": "Thomas Edison",
    "title": "Inventor"
  },
  {
    "quote": "A person who never made a mistake never tried anything new.",
    "author": "Albert Einstein",
    "title": "Theoretical Physicist"
  },
  {
    "quote": "The person who says it cannot be done should not interrupt the person who is doing it.",
    "author": "Chinese Proverb",
    "title": "Ancient Wisdom"
  },
  {
    "quote": "Love all, trust a few, do wrong to none.",
    "author": "William Shakespeare",
    "title": "Playwright & Poet"
  },
  {
    "quote": "All the world's a stage, and all the men and women merely players.",
    "author": "William Shakespeare",
    "title": "Playwright & Poet"
  },
  {
    "quote": "This above all: to thine own self be true.",
    "author": "William Shakespeare",
    "title": "Playwright & Poet"
  },
  {
    "quote": "We know what we are, but know not what we may be.",
    "author": "William Shakespeare",
    "title": "Playwright & Poet"
  },
  {
    "quote": "The course of true love never did run smooth.",
    "author": "William Shakespeare",
    "title": "Playwright & Poet"
  },
  {
    "quote": "The better part of one's life consists of his friendships.",
    "author": "Abraham Lincoln",
    "title": "16th U.S. President"
  },
  {
    "quote": "I am not bound to win, but I am bound to be true.",
    "author": "Abraham Lincoln",
    "title": "16th U.S. President"
  },
  {
    "quote": "Whatever you are, be a good one.",
    "author": "Abraham Lincoln",
    "title": "16th U.S. President"
  },
  {
    "quote": "Nearly all men can stand adversity, but if you want to test a man's character, give him power.",
    "author": "Abraham Lincoln",
    "title": "16th U.S. President"
  },
  {
    "quote": "The only way to have a friend is to be one.",
    "author": "Ralph Waldo Emerson",
    "title": "Philosopher & Poet"
  },
  {
    "quote": "To be yourself in a world that is constantly trying to make you something else is the greatest accomplishment.",
    "author": "Ralph Waldo Emerson",
    "title": "Philosopher & Poet"
  },
  {
    "quote": "Write it on your heart that every day is the best day in the year.",
    "author": "Ralph Waldo Emerson",
    "title": "Philosopher & Poet"
  },
  {
    "quote": "For every minute you are angry you lose sixty seconds of happiness.",
    "author": "Ralph Waldo Emerson",
    "title": "Philosopher & Poet"
  },
  {
    "quote": "What lies behind us and what lies before us are tiny matters compared to what lies within us.",
    "author": "Ralph Waldo Emerson",
    "title": "Philosopher & Poet"
  },
  {
    "quote": "We accept the love we think we deserve.",
    "author": "Stephen Chbosky",
    "title": "Author"
  },
  {
    "quote": "It is better to be hated for what you are than to be loved for what you are not.",
    "author": "André Gide",
    "title": "Author & Nobel Laureate"
  },
  {
    "quote": "There is no greater agony than bearing an untold story inside you.",
    "author": "Maya Angelou",
    "title": "Poet & Civil Rights Activist"
  },
  {
    "quote": "If you don't like something, change it. If you can't change it, change your attitude.",
    "author": "Maya Angelou",
    "title": "Poet & Civil Rights Activist"
  },
  {
    "quote": "I've learned that people will forget what you said, people will forget what you did, but people will never forget how you made them feel.",
    "author": "Maya Angelou",
    "title": "Poet & Civil Rights Activist"
  },
  {
    "quote": "Try to be a rainbow in someone's cloud.",
    "author": "Maya Angelou",
    "title": "Poet & Civil Rights Activist"
  },
  {
    "quote": "Success is liking yourself, liking what you do, and liking how you do it.",
    "author": "Maya Angelou",
    "title": "Poet & Civil Rights Activist"
  },
  {
    "quote": "There is nothing either good or bad, but thinking makes it so.",
    "author": "William Shakespeare",
    "title": "Playwright & Poet"
  },
  {
    "quote": "The weak can never forgive. Forgiveness is the attribute of the strong.",
    "author": "Mahatma Gandhi",
    "title": "Independence Leader & Philosopher"
  },
  {
    "quote": "Live as if you were to die tomorrow. Learn as if you were to live forever.",
    "author": "Mahatma Gandhi",
    "title": "Independence Leader & Philosopher"
  },
  {
    "quote": "An eye for an eye only ends up making the whole world blind.",
    "author": "Mahatma Gandhi",
    "title": "Independence Leader & Philosopher"
  },
  {
    "quote": "Happiness is when what you think, what you say, and what you do are in harmony.",
    "author": "Mahatma Gandhi",
    "title": "Independence Leader & Philosopher"
  },
  {
    "quote": "Freedom is not worth having if it does not include the freedom to make mistakes.",
    "author": "Mahatma Gandhi",
    "title": "Independence Leader & Philosopher"
  },
  {
    "quote": "The greatness of a nation can be judged by the way its animals are treated.",
    "author": "Mahatma Gandhi",
    "title": "Independence Leader & Philosopher"
  },
  {
    "quote": "Faith is taking the first step even when you don't see the whole staircase.",
    "author": "Martin Luther King Jr.",
    "title": "Civil Rights Leader"
  },
  {
    "quote": "Injustice anywhere is a threat to justice everywhere.",
    "author": "Martin Luther King Jr.",
    "title": "Civil Rights Leader"
  },
  {
    "quote": "Our lives begin to end the day we become silent about things that matter.",
    "author": "Martin Luther King Jr.",
    "title": "Civil Rights Leader"
  },
  {
    "quote": "The time is always right to do what is right.",
    "author": "Martin Luther King Jr.",
    "title": "Civil Rights Leader"
  },
  {
    "quote": "Intelligence plus character—that is the goal of true education.",
    "author": "Martin Luther King Jr.",
    "title": "Civil Rights Leader"
  },
  {
    "quote": "Life's most persistent and urgent question is, 'What are you doing for others?'",
    "author": "Martin Luther King Jr.",
    "title": "Civil Rights Leader"
  },
  {
    "quote": "I have decided to stick with love. Hate is too great a burden to bear.",
    "author": "Martin Luther King Jr.",
    "title": "Civil Rights Leader"
  },
  {
    "quote": "The ultimate measure of a man is not where he stands in moments of comfort, but where he stands at times of challenge and controversy.",
    "author": "Martin Luther King Jr.",
    "title": "Civil Rights Leader"
  },
  {
    "quote": "We must accept finite disappointment, but never lose infinite hope.",
    "author": "Martin Luther King Jr.",
    "title": "Civil Rights Leader"
  },
  {
    "quote": "Courageous people do not fear forgiving, for the sake of peace.",
    "author": "Nelson Mandela",
    "title": "Anti-Apartheid Revolutionary & President"
  },
  {
    "quote": "I learned that courage was not the absence of fear, but the triumph over it.",
    "author": "Nelson Mandela",
    "title": "Anti-Apartheid Revolutionary & President"
  },
  {
    "quote": "Resentment is like drinking poison and then hoping it will kill your enemies.",
    "author": "Nelson Mandela",
    "title": "Anti-Apartheid Revolutionary & President"
  },
  {
    "quote": "A good head and a good heart are always a formidable combination.",
    "author": "Nelson Mandela",
    "title": "Anti-Apartheid Revolutionary & President"
  },
  {
    "quote": "The greatest glory in living lies not in never falling, but in rising every time we fall.",
    "author": "Nelson Mandela",
    "title": "Anti-Apartheid Revolutionary & President"
  },
  {
    "quote": "For to be free is not merely to cast off one's chains, but to live in a way that respects and enhances the freedom of others.",
    "author": "Nelson Mandela",
    "title": "Anti-Apartheid Revolutionary & President"
  },
  {
    "quote": "If you talk to a man in a language he understands, that goes to his head. If you talk to him in his language, that goes to his heart.",
    "author": "Nelson Mandela",
    "title": "Anti-Apartheid Revolutionary & President"
  },
  {
    "quote": "A winner is a dreamer who never gives up.",
    "author": "Nelson Mandela",
    "title": "Anti-Apartheid Revolutionary & President"
  },
  {
    "quote": "Logic will get you from A to B. Imagination will take you everywhere.",
    "author": "Albert Einstein",
    "title": "Theoretical Physicist"
  },
  {
    "quote": "Life is like riding a bicycle. To keep your balance, you must keep moving.",
    "author": "Albert Einstein",
    "title": "Theoretical Physicist"
  },
  {
    "quote": "Anyone who has never made a mistake has never tried anything new.",
    "author": "Albert Einstein",
    "title": "Theoretical Physicist"
  },
  {
    "quote": "Try not to become a man of success. Rather become a man of value.",
    "author": "Albert Einstein",
    "title": "Theoretical Physicist"
  },
  {
    "quote": "The important thing is not to stop questioning. Curiosity has its own reason for existing.",
    "author": "Albert Einstein",
    "title": "Theoretical Physicist"
  },
  {
    "quote": "Imagination is more important than knowledge.",
    "author": "Albert Einstein",
    "title": "Theoretical Physicist"
  },
  {
    "quote": "A clever person solves a problem. A wise person avoids it.",
    "author": "Albert Einstein",
    "title": "Theoretical Physicist"
  },
  {
    "quote": "Peace cannot be kept by force; it can only be achieved by understanding.",
    "author": "Albert Einstein",
    "title": "Theoretical Physicist"
  },
  {
    "quote": "The world as we have created it is a process of our thinking. It cannot be changed without changing our thinking.",
    "author": "Albert Einstein",
    "title": "Theoretical Physicist"
  },
  {
    "quote": "We cannot solve our problems with the same thinking we used when we created them.",
    "author": "Albert Einstein",
    "title": "Theoretical Physicist"
  },
  {
    "quote": "Two things are infinite: the universe and human stupidity; and I'm not sure about the universe.",
    "author": "Albert Einstein",
    "title": "Theoretical Physicist"
  },
  {
    "quote": "Be curious, not judgmental.",
    "author": "Walt Whitman",
    "title": "Poet"
  },
  {
    "quote": "Keep your face always toward the sunshine—and shadows will fall behind you.",
    "author": "Walt Whitman",
    "title": "Poet"
  },
  {
    "quote": "We were together. I forget the rest.",
    "author": "Walt Whitman",
    "title": "Poet"
  },
  {
    "quote": "I am large, I contain multitudes.",
    "author": "Walt Whitman",
    "title": "Poet"
  },
  {
    "quote": "Happiness is not by chance, but by choice.",
    "author": "Jim Rohn",
    "title": "Entrepreneur & Motivational Speaker"
  },
  {
    "quote": "Either you run the day, or the day runs you.",
    "author": "Jim Rohn",
    "title": "Entrepreneur & Motivational Speaker"
  },
  {
    "quote": "Don't wish it were easier; wish you were better.",
    "author": "Jim Rohn",
    "title": "Entrepreneur & Motivational Speaker"
  },
  {
    "quote": "You are the average of the five people you spend the most time with.",
    "author": "Jim Rohn",
    "title": "Entrepreneur & Motivational Speaker"
  },
  {
    "quote": "Success is nothing more than a few simple disciplines, practiced every day.",
    "author": "Jim Rohn",
    "title": "Entrepreneur & Motivational Speaker"
  },
  {
    "quote": "The only limit to our realization of tomorrow will be our doubts of today.",
    "author": "Franklin D. Roosevelt",
    "title": "32nd U.S. President"
  },
  {
    "quote": "When you reach the end of your rope, tie a knot in it and hang on.",
    "author": "Franklin D. Roosevelt",
    "title": "32nd U.S. President"
  },
  {
    "quote": "The only thing we have to fear is fear itself.",
    "author": "Franklin D. Roosevelt",
    "title": "32nd U.S. President"
  },
  {
    "quote": "We gain strength, and courage, and confidence by each experience in which we really stop to look fear in the face.",
    "author": "Eleanor Roosevelt",
    "title": "Diplomat & Human Rights Advocate"
  },
  {
    "quote": "Do one thing every day that scares you.",
    "author": "Eleanor Roosevelt",
    "title": "Diplomat & Human Rights Advocate"
  },
  {
    "quote": "No one can make you feel inferior without your consent.",
    "author": "Eleanor Roosevelt",
    "title": "Diplomat & Human Rights Advocate"
  },
  {
    "quote": "The purpose of life is not to be happy. It is to be useful, to be honorable, to be compassionate.",
    "author": "Ralph Waldo Emerson",
    "title": "Philosopher & Poet"
  },
  {
    "quote": "Great minds discuss ideas; average minds discuss events; small minds discuss people.",
    "author": "Eleanor Roosevelt",
    "title": "Diplomat & Human Rights Advocate"
  },
  {
    "quote": "You must do the things you think you cannot do.",
    "author": "Eleanor Roosevelt",
    "title": "Diplomat & Human Rights Advocate"
  },
  {
    "quote": "It is better to light a candle than curse the darkness.",
    "author": "Eleanor Roosevelt",
    "title": "Diplomat & Human Rights Advocate"
  },
  {
    "quote": "Let us remember: One book, one pen, one child, and one teacher can change the world.",
    "author": "Malala Yousafzai",
    "title": "Education Activist & Nobel Laureate"
  },
  {
    "quote": "When the whole world is silent, even one voice becomes powerful.",
    "author": "Malala Yousafzai",
    "title": "Education Activist & Nobel Laureate"
  },
  {
    "quote": "We realize the importance of our voices only when we are silenced.",
    "author": "Malala Yousafzai",
    "title": "Education Activist & Nobel Laureate"
  },
  {
    "quote": "If you are neutral in situations of injustice, you have chosen the side of the oppressor.",
    "author": "Desmond Tutu",
    "title": "Archbishop & Human Rights Activist"
  },
  {
    "quote": "Do your little bit of good where you are; it's those little bits of good put together that overwhelm the world.",
    "author": "Desmond Tutu",
    "title": "Archbishop & Human Rights Activist"
  },
  {
    "quote": "Hope is being able to see that there is light despite all of the darkness.",
    "author": "Desmond Tutu",
    "title": "Archbishop & Human Rights Activist"
  },
  {
    "quote": "We are made for goodness. We are made for love. We are made for friendliness.",
    "author": "Desmond Tutu",
    "title": "Archbishop & Human Rights Activist"
  },
  {
    "quote": "Courage is not the absence of fear, but rather the assessment that something else is more important than fear.",
    "author": "Franklin D. Roosevelt",
    "title": "32nd U.S. President"
  },
  {
    "quote": "Judge a man by his questions rather than by his answers.",
    "author": "Voltaire",
    "title": "Philosopher & Writer"
  },
  {
    "quote": "Common sense is not so common.",
    "author": "Voltaire",
    "title": "Philosopher & Writer"
  },
  {
    "quote": "Don't let perfection become procrastination. Do it now.",
    "author": "Danielle LaPorte",
    "title": "Author & Motivational Speaker"
  },
  {
    "quote": "Knowing yourself is the beginning of all wisdom.",
    "author": "Aristotle",
    "title": "Philosopher"
  },
  {
    "quote": "It is the mark of an educated mind to be able to entertain a thought without accepting it.",
    "author": "Aristotle",
    "title": "Philosopher"
  },
  {
    "quote": "Quality is not an act, it is a habit.",
    "author": "Aristotle",
    "title": "Philosopher"
  },
  {
    "quote": "The roots of education are bitter, but the fruit is sweet.",
    "author": "Aristotle",
    "title": "Philosopher"
  },
  {
    "quote": "Patience is bitter, but its fruit is sweet.",
    "author": "Aristotle",
    "title": "Philosopher"
  },
  {
    "quote": "Hope is a waking dream.",
    "author": "Aristotle",
    "title": "Philosopher"
  },
  {
    "quote": "The whole is greater than the sum of its parts.",
    "author": "Aristotle",
    "title": "Philosopher"
  },
  {
    "quote": "Those who know, do. Those that understand, teach.",
    "author": "Aristotle",
    "title": "Philosopher"
  },
  {
    "quote": "The energy of the mind is the essence of life.",
    "author": "Aristotle",
    "title": "Philosopher"
  },
  {
    "quote": "Pleasure in the job puts perfection in the work.",
    "author": "Aristotle",
    "title": "Philosopher"
  },
  {
    "quote": "Hope is the dream of a waking man.",
    "author": "Aristotle",
    "title": "Philosopher"
  },
  {
    "quote": "Educating the mind without educating the heart is no education at all.",
    "author": "Aristotle",
    "title": "Philosopher"
  },
  {
    "quote": "The cure for boredom is curiosity. There is no cure for curiosity.",
    "author": "Dorothy Parker",
    "title": "Poet & Writer"
  },
  {
    "quote": "You can't use up creativity. The more you use, the more you have.",
    "author": "Maya Angelou",
    "title": "Poet & Civil Rights Activist"
  },
  {
    "quote": "My mission in life is not merely to survive, but to thrive.",
    "author": "Maya Angelou",
    "title": "Poet & Civil Rights Activist"
  },
  {
    "quote": "Nothing will work unless you do.",
    "author": "Maya Angelou",
    "title": "Poet & Civil Rights Activist"
  },
  {
    "quote": "Have enough courage to start and enough heart to finish.",
    "author": "Jessica N. S. Yourko",
    "title": "Author"
  },
  {
    "quote": "What you get by achieving your goals is not as important as what you become by achieving your goals.",
    "author": "Zig Ziglar",
    "title": "Motivational Speaker"
  },
  {
    "quote": "You don't have to be great to start, but you have to start to be great.",
    "author": "Zig Ziglar",
    "title": "Motivational Speaker"
  },
  {
    "quote": "People often say that motivation doesn't last. Well, neither does bathing. That's why we recommend it daily.",
    "author": "Zig Ziglar",
    "title": "Motivational Speaker"
  },
  {
    "quote": "A goal properly set is halfway reached.",
    "author": "Zig Ziglar",
    "title": "Motivational Speaker"
  },
  {
    "quote": "You were born to win, but to be a winner you must plan to win, prepare to win, and expect to win.",
    "author": "Zig Ziglar",
    "title": "Motivational Speaker"
  },
  {
    "quote": "The difference between ordinary and extraordinary is that little extra.",
    "author": "Jimmy Johnson",
    "title": "Football Coach"
  },
  {
    "quote": "Start where you are. Use what you have. Do what you can.",
    "author": "Arthur Ashe",
    "title": "Tennis Champion & Activist"
  },
  {
    "quote": "Success is a journey, not a destination. The doing is often more important than the outcome.",
    "author": "Arthur Ashe",
    "title": "Tennis Champion & Activist"
  },
  {
    "quote": "True heroism is remarkably sober, very undramatic. It is not the urge to surpass all others at whatever cost, but the urge to serve others at whatever cost.",
    "author": "Arthur Ashe",
    "title": "Tennis Champion & Activist"
  },
  {
    "quote": "From what we get, we can make a living; what we give, however, makes a life.",
    "author": "Arthur Ashe",
    "title": "Tennis Champion & Activist"
  },
  {
    "quote": "A ship in harbor is safe, but that is not what ships are built for.",
    "author": "John A. Shedd",
    "title": "Author"
  },
  {
    "quote": "The most common way people give up their power is by thinking they don't have any.",
    "author": "Alice Walker",
    "title": "Author & Activist"
  },
  {
    "quote": "The most beautiful things in the world cannot be seen or even touched, they must be felt with the heart.",
    "author": "Helen Keller",
    "title": "Author & Disability Rights Advocate"
  },
  {
    "quote": "Alone we can do so little; together we can do so much.",
    "author": "Helen Keller",
    "title": "Author & Disability Rights Advocate"
  },
  {
    "quote": "Optimism is the faith that leads to achievement. Nothing can be done without hope and confidence.",
    "author": "Helen Keller",
    "title": "Author & Disability Rights Advocate"
  },
  {
    "quote": "The best and most beautiful things in the world cannot be seen or even touched - they must be felt with the heart.",
    "author": "Helen Keller",
    "title": "Author & Disability Rights Advocate"
  },
  {
    "quote": "Keep your face to the sunshine and you cannot see a shadow.",
    "author": "Helen Keller",
    "title": "Author & Disability Rights Advocate"
  },
  {
    "quote": "Although the world is full of suffering, it is also full of the overcoming of it.",
    "author": "Helen Keller",
    "title": "Author & Disability Rights Advocate"
  },
  {
    "quote": "Walking with a friend in the dark is better than walking alone in the light.",
    "author": "Helen Keller",
    "title": "Author & Disability Rights Advocate"
  },
  {
    "quote": "What we think, we become.",
    "author": "Buddha",
    "title": "Spiritual Teacher"
  },
  {
    "quote": "Peace comes from within. Do not seek it without.",
    "author": "Buddha",
    "title": "Spiritual Teacher"
  },
  {
    "quote": "You yourself, as much as anybody in the entire universe, deserve your love and affection.",
    "author": "Buddha",
    "title": "Spiritual Teacher"
  },
  {
    "quote": "Holding on to anger is like grasping a hot coal with the intent of throwing it at someone else; you are the one who gets burned.",
    "author": "Buddha",
    "title": "Spiritual Teacher"
  },
  {
    "quote": "Three things cannot be long hidden: the sun, the moon, and the truth.",
    "author": "Buddha",
    "title": "Spiritual Teacher"
  },
  {
    "quote": "No one saves us but ourselves. No one can and no one may. We ourselves must walk the path.",
    "author": "Buddha",
    "title": "Spiritual Teacher"
  },
  {
    "quote": "Health is the greatest gift, contentment the greatest wealth, faithfulness the best relationship.",
    "author": "Buddha",
    "title": "Spiritual Teacher"
  },
  {
    "quote": "Let us rise up and be thankful, for if we didn't learn a lot today, at least we learned a little.",
    "author": "Buddha",
    "title": "Spiritual Teacher"
  },
  {
    "quote": "Better than a thousand hollow words, is one word that brings peace.",
    "author": "Buddha",
    "title": "Spiritual Teacher"
  },
  {
    "quote": "The trouble is, you think you have time.",
    "author": "Buddha",
    "title": "Spiritual Teacher"
  },
  {
    "quote": "A jug fills drop by drop.",
    "author": "Buddha",
    "title": "Spiritual Teacher"
  },
  {
    "quote": "Spread love everywhere you go. Let no one ever come to you without leaving happier.",
    "author": "Mother Teresa",
    "title": "Humanitarian & Saint"
  },
  {
    "quote": "Not all of us can do great things. But we can do small things with great love.",
    "author": "Mother Teresa",
    "title": "Humanitarian & Saint"
  },
  {
    "quote": "If you judge people, you have no time to love them.",
    "author": "Mother Teresa",
    "title": "Humanitarian & Saint"
  },
  {
    "quote": "Kind words can be short and easy to speak, but their echoes are truly endless.",
    "author": "Mother Teresa",
    "title": "Humanitarian & Saint"
  },
  {
    "quote": "Peace begins with a smile.",
    "author": "Mother Teresa",
    "title": "Humanitarian & Saint"
  },
  {
    "quote": "Let us always meet each other with smile, for the smile is the beginning of love.",
    "author": "Mother Teresa",
    "title": "Humanitarian & Saint"
  },
  {
    "quote": "I alone cannot change the world, but I can cast a stone across the waters to create many ripples.",
    "author": "Mother Teresa",
    "title": "Humanitarian & Saint"
  },
  {
    "quote": "Yesterday is gone. Tomorrow has not yet come. We have only today. Let us begin.",
    "author": "Mother Teresa",
    "title": "Humanitarian & Saint"
  },
  {
    "quote": "Be happy in the moment, that's enough. Each moment is all we need, not more.",
    "author": "Mother Teresa",
    "title": "Humanitarian & Saint"
  },
  {
    "quote": "The biggest disease this day and age is that of people feeling unloved.",
    "author": "Mother Teresa",
    "title": "Humanitarian & Saint"
  },
  {
    "quote": "When I do good, I feel good. When I do bad, I feel bad. That's my religion.",
    "author": "Abraham Lincoln",
    "title": "16th U.S. President"
  },
  {
    "quote": "I walk slowly, but I never walk backward.",
    "author": "Abraham Lincoln",
    "title": "16th U.S. President"
  },
  {
    "quote": "The best way to predict your future is to create it.",
    "author": "Abraham Lincoln",
    "title": "16th U.S. President"
  },
  {
    "quote": "Character is like a tree and reputation like a shadow. The shadow is what we think of it; the tree is the real thing.",
    "author": "Abraham Lincoln",
    "title": "16th U.S. President"
  },
  {
    "quote": "Give me six hours to chop down a tree and I will spend the first four sharpening the axe.",
    "author": "Abraham Lincoln",
    "title": "16th U.S. President"
  },
  {
    "quote": "Whatever you are, be a good one.",
    "author": "Abraham Lincoln",
    "title": "16th U.S. President"
  },
  {
    "quote": "I'm a success today because I had a friend who believed in me and I didn't have the heart to let him down.",
    "author": "Abraham Lincoln",
    "title": "16th U.S. President"
  },
  {
    "quote": "Be sure you put your feet in the right place, then stand firm.",
    "author": "Abraham Lincoln",
    "title": "16th U.S. President"
  },
  {
    "quote": "You can tell the greatness of a man by what makes him angry.",
    "author": "Abraham Lincoln",
    "title": "16th U.S. President"
  },
  {
    "quote": "No man has a good enough memory to be a successful liar.",
    "author": "Abraham Lincoln",
    "title": "16th U.S. President"
  },
  {
    "quote": "All that we are is the result of what we have thought.",
    "author": "Buddha",
    "title": "Spiritual Teacher"
  },
  {
    "quote": "The only real mistake is the one from which we learn nothing.",
    "author": "Henry Ford",
    "title": "Industrialist & Innovator"
  },
  {
    "quote": "Whether you think you can or you think you can't, you're right.",
    "author": "Henry Ford",
    "title": "Industrialist & Innovator"
  },
  {
    "quote": "Failure is simply the opportunity to begin again, this time more intelligently.",
    "author": "Henry Ford",
    "title": "Industrialist & Innovator"
  },
  {
    "quote": "Coming together is a beginning. Keeping together is progress. Working together is success.",
    "author": "Henry Ford",
    "title": "Industrialist & Innovator"
  },
  {
    "quote": "Don't find fault, find a remedy.",
    "author": "Henry Ford",
    "title": "Industrialist & Innovator"
  },
  {
    "quote": "Quality means doing it right when no one is looking.",
    "author": "Henry Ford",
    "title": "Industrialist & Innovator"
  },
  {
    "quote": "Anyone who stops learning is old, whether at twenty or eighty. Anyone who keeps learning stays young.",
    "author": "Henry Ford",
    "title": "Industrialist & Innovator"
  },
  {
    "quote": "Vision without execution is just hallucination.",
    "author": "Henry Ford",
    "title": "Industrialist & Innovator"
  },
  {
    "quote": "You can't build a reputation on what you are going to do.",
    "author": "Henry Ford",
    "title": "Industrialist & Innovator"
  },
  {
    "quote": "Obstacles are those frightful things you see when you take your eyes off your goal.",
    "author": "Henry Ford",
    "title": "Industrialist & Innovator"
  },
  {
    "quote": "Innovation distinguishes between a leader and a follower.",
    "author": "Steve Jobs",
    "title": "Technology Innovator"
  },
  {
    "quote": "Stay hungry, stay foolish.",
    "author": "Steve Jobs",
    "title": "Technology Innovator"
  },
  {
    "quote": "The people who are crazy enough to think they can change the world are the ones who do.",
    "author": "Steve Jobs",
    "title": "Technology Innovator"
  },
  {
    "quote": "Design is not just what it looks like and feels like. Design is how it works.",
    "author": "Steve Jobs",
    "title": "Technology Innovator"
  },
  {
    "quote": "Quality is more important than quantity. One home run is much better than two doubles.",
    "author": "Steve Jobs",
    "title": "Technology Innovator"
  },
  {
    "quote": "Sometimes life is going to hit you in the head with a brick. Don't lose faith.",
    "author": "Steve Jobs",
    "title": "Technology Innovator"
  },
  {
    "quote": "I'm convinced that about half of what separates successful entrepreneurs from the non-successful ones is pure perseverance.",
    "author": "Steve Jobs",
    "title": "Technology Innovator"
  },
  {
    "quote": "Simple can be harder than complex. You have to work hard to get your thinking clean to make it simple.",
    "author": "Steve Jobs",
    "title": "Technology Innovator"
  },
  {
    "quote": "Remembering that you are going to die is the best way I know to avoid the trap of thinking you have something to lose.",
    "author": "Steve Jobs",
    "title": "Technology Innovator"
  },
  {
    "quote": "Have the courage to follow your heart and intuition. They somehow know what you truly want to become.",
    "author": "Steve Jobs",
    "title": "Technology Innovator"
  },
  {
    "quote": "Don't be trapped by dogma — which is living with the results of other people's thinking.",
    "author": "Steve Jobs",
    "title": "Technology Innovator"
  },
  {
    "quote": "My favorite things in life don't cost any money. It's really clear that the most precious resource we all have is time.",
    "author": "Steve Jobs",
    "title": "Technology Innovator"
  },
  {
    "quote": "Be a yardstick of quality. Some people aren't used to an environment where excellence is expected.",
    "author": "Steve Jobs",
    "title": "Technology Innovator"
  },
  {
    "quote": "You can't connect the dots looking forward; you can only connect them looking backwards.",
    "author": "Steve Jobs",
    "title": "Technology Innovator"
  },
  {
    "quote": "The real test is not whether you avoid this failure, because you won't. It's whether you let it harden or shame you into inaction.",
    "author": "Barack Obama",
    "title": "44th U.S. President"
  },
  {
    "quote": "Change will not come if we wait for some other person or some other time. We are the ones we've been waiting for.",
    "author": "Barack Obama",
    "title": "44th U.S. President"
  },
  {
    "quote": "The best way to not feel hopeless is to get up and do something.",
    "author": "Barack Obama",
    "title": "44th U.S. President"
  },
  {
    "quote": "We are the change that we seek.",
    "author": "Barack Obama",
    "title": "44th U.S. President"
  },
  {
    "quote": "If you're walking down the right path and you're willing to keep walking, eventually you'll make progress.",
    "author": "Barack Obama",
    "title": "44th U.S. President"
  },
  {
    "quote": "The future rewards those who press on. I don't have time to feel sorry for myself. I don't have time to complain. I'm going to press on.",
    "author": "Barack Obama",
    "title": "44th U.S. President"
  },
  {
    "quote": "Our destiny is not written for us, but by us.",
    "author": "Barack Obama",
    "title": "44th U.S. President"
  },
  {
    "quote": "The only thing that is the end of the world is the end of the world.",
    "author": "Barack Obama",
    "title": "44th U.S. President"
  },
  {
    "quote": "Be humble. Be hungry. And always be the hardest worker in the room.",
    "author": "Dwayne Johnson",
    "title": "Actor & Former Athlete"
  },
  {
    "quote": "Success isn't always about greatness. It's about consistency. Consistent hard work leads to success.",
    "author": "Dwayne Johnson",
    "title": "Actor & Former Athlete"
  },
  {
    "quote": "Blood, sweat, and respect. First two you give, last one you earn.",
    "author": "Dwayne Johnson",
    "title": "Actor & Former Athlete"
  },
  {
    "quote": "Don't be afraid to be ambitious about your goals. Hard work never stops.",
    "author": "Dwayne Johnson",
    "title": "Actor & Former Athlete"
  },
  {
    "quote": "All successes begin with self-discipline. It starts with you.",
    "author": "Dwayne Johnson",
    "title": "Actor & Former Athlete"
  },
  {
    "quote": "Seek respect, not attention. It lasts longer.",
    "author": "Ziad K. Abdelnour",
    "title": "Entrepreneur & Author"
  },
  {
    "quote": "A reader lives a thousand lives before he dies. The man who never reads lives only one.",
    "author": "George R.R. Martin",
    "title": "Author"
  },
  {
    "quote": "When you play the game of thrones, you win or you die. There is no middle ground.",
    "author": "George R.R. Martin",
    "title": "Author"
  },
  {
    "quote": "We should not judge people by their peak of excellence; but by the distance they have traveled from the point where they started.",
    "author": "Henry Ward Beecher",
    "title": "Clergyman & Social Reformer"
  },
  {
    "quote": "Every man is guilty of all the good he did not do.",
    "author": "Voltaire",
    "title": "Philosopher & Writer"
  },
  {
    "quote": "Life is really simple, but we insist on making it complicated.",
    "author": "Confucius",
    "title": "Philosopher"
  },
  {
    "quote": "Our greatest glory is not in never falling, but in rising every time we fall.",
    "author": "Confucius",
    "title": "Philosopher"
  },
  {
    "quote": "It does not matter how slowly you go as long as you do not stop.",
    "author": "Confucius",
    "title": "Philosopher"
  },
  {
    "quote": "The man who moves a mountain begins by carrying away small stones.",
    "author": "Confucius",
    "title": "Philosopher"
  },
  {
    "quote": "When it is obvious that the goals cannot be reached, don't adjust the goals, adjust the action steps.",
    "author": "Confucius",
    "title": "Philosopher"
  },
  {
    "quote": "Wheresoever you go, go with all your heart.",
    "author": "Confucius",
    "title": "Philosopher"
  },
  {
    "quote": "Real knowledge is to know the extent of one's ignorance.",
    "author": "Confucius",
    "title": "Philosopher"
  },
  {
    "quote": "I hear and I forget. I see and I remember. I do and I understand.",
    "author": "Confucius",
    "title": "Philosopher"
  },
  {
    "quote": "Everything has beauty, but not everyone sees it.",
    "author": "Confucius",
    "title": "Philosopher"
  },
  {
    "quote": "The will to win, the desire to succeed, the urge to reach your full potential... these are the keys that will unlock the door to personal excellence.",
    "author": "Confucius",
    "title": "Philosopher"
  },
  {
    "quote": "To see what is right and not do it is a lack of courage.",
    "author": "Confucius",
    "title": "Philosopher"
  },
  {
    "quote": "Before you embark on a journey of revenge, dig two graves.",
    "author": "Confucius",
    "title": "Philosopher"
  },
  {
    "quote": "Silence is a true friend who never betrays.",
    "author": "Confucius",
    "title": "Philosopher"
  },
  {
    "quote": "When anger rises, think of the consequences.",
    "author": "Confucius",
    "title": "Philosopher"
  },
  {
    "quote": "Study the past if you would define the future.",
    "author": "Confucius",
    "title": "Philosopher"
  },
  {
    "quote": "Respect yourself and others will respect you.",
    "author": "Confucius",
    "title": "Philosopher"
  },
  {
    "quote": "Choose a job you love, and you will never have to work a day in your life.",
    "author": "Confucius",
    "title": "Philosopher"
  },
  {
    "quote": "He who knows all the answers has not been asked all the questions.",
    "author": "Confucius",
    "title": "Philosopher"
  },
  {
    "quote": "The superior man is modest in his speech but exceeds in his actions.",
    "author": "Confucius",
    "title": "Philosopher"
  },
  {
    "quote": "The man who asks a question is a fool for a minute, the man who does not ask is a fool for life.",
    "author": "Confucius",
    "title": "Philosopher"
  },
  {
    "quote": "The wound is the place where the Light enters you.",
    "author": "Rumi",
    "title": "Poet & Mystic"
  },
  {
    "quote": "Yesterday I was clever, so I wanted to change the world. Today I am wise, so I am changing myself.",
    "author": "Rumi",
    "title": "Poet & Mystic"
  },
  {
    "quote": "Don't grieve. Anything you lose comes round in another form.",
    "author": "Rumi",
    "title": "Poet & Mystic"
  },
  {
    "quote": "Let yourself be silently drawn by the strange pull of what you really love. It will not lead you astray.",
    "author": "Rumi",
    "title": "Poet & Mystic"
  },
  {
    "quote": "The universe is not outside of you. Look inside yourself; everything that you want, you already are.",
    "author": "Rumi",
    "title": "Poet & Mystic"
  },
  {
    "quote": "Stop acting so small. You are the universe in ecstatic motion.",
    "author": "Rumi",
    "title": "Poet & Mystic"
  },
  {
    "quote": "What you seek is seeking you.",
    "author": "Rumi",
    "title": "Poet & Mystic"
  },
  {
    "quote": "The lion is most handsome when looking for food.",
    "author": "Rumi",
    "title": "Poet & Mystic"
  },
  {
    "quote": "Set your life on fire. Seek those who fan your flames.",
    "author": "Rumi",
    "title": "Poet & Mystic"
  },
  {
    "quote": "When you do things from your soul, you feel a river moving in you, a joy.",
    "author": "Rumi",
    "title": "Poet & Mystic"
  },
  {
    "quote": "Raise your words, not voice. It is rain that grows flowers, not thunder.",
    "author": "Rumi",
    "title": "Poet & Mystic"
  },
  {
    "quote": "There is a voice that doesn't use words. Listen.",
    "author": "Rumi",
    "title": "Poet & Mystic"
  },
  {
    "quote": "Let the beauty we love be what we do.",
    "author": "Rumi",
    "title": "Poet & Mystic"
  },
  {
    "quote": "Sell your cleverness and buy bewilderment.",
    "author": "Rumi",
    "title": "Poet & Mystic"
  },
  {
    "quote": "The art of knowing is knowing what to ignore.",
    "author": "Rumi",
    "title": "Poet & Mystic"
  },
  {
    "quote": "Goodbyes are only for those who love with their eyes. Because for those who love with heart and soul there is no such thing as separation.",
    "author": "Rumi",
    "title": "Poet & Mystic"
  },
  {
    "quote": "Be grateful for whoever comes, because each has been sent as a guide from beyond.",
    "author": "Rumi",
    "title": "Poet & Mystic"
  },
  {
    "quote": "Travel brings power and love back into your life.",
    "author": "Rumi",
    "title": "Poet & Mystic"
  },
  {
    "quote": "Wherever you stand, be the soul of that place.",
    "author": "Rumi",
    "title": "Poet & Mystic"
  }
]

